pd_replicator/__init__.py
pd_replicator/widgets/__init__.py
pd_replicator/widgets/constants.py
pd_replicator/widgets/html.py
pd_replicator/widgets/html_copy_button.py
pd_replicator/widgets/native_copy_button.py
pd_replicator-0.0.1.dist-info/LICENSE
pd_replicator-0.0.1.dist-info/METADATA
pd_replicator-0.0.1.dist-info/WHEEL
pd_replicator-0.0.1.dist-info/top_level.txt
pd_replicator-0.0.1.dist-info/RECORD
