Metadata-Version: 2.1
Name: pd-replicator
Version: 0.0.1
Summary: Copy a pandas DataFrame to the clipboard with one click
Home-page: https://github.com/scwilkinson/pd-replicator
Author: Sam Wilkinson
Author-email: hello@samwilkinson.io
License: UNKNOWN
Platform: UNKNOWN
Classifier: Programming Language :: Python :: 3
Classifier: License :: OSI Approved :: GNU General Public License v3 (GPLv3)
Classifier: Operating System :: OS Independent
Requires-Python: >=3.6
Requires-Dist: pandas
Requires-Dist: ipywidgets
Requires-Dist: ipython
